primpy/__init__.py
primpy/__version__.py
primpy/bigbang.py
primpy/equations.py
primpy/events.py
primpy/exceptionhandling.py
primpy/inflation.py
primpy/initialconditions.py
primpy/oscode_solver.py
primpy/parameters.py
primpy/perturbations.py
primpy/potentials.py
primpy/reheating.py
primpy/solver.py
primpy/units.py
primpy/efolds/__init__.py
primpy/efolds/inflation.py
primpy/efolds/perturbations.py
primpy/time/__init__.py
primpy/time/inflation.py
primpy/time/perturbations.py
primpy-2.18.2.dist-info/licenses/LICENSE
tests/__init__.py
tests/test_bigbang.py
tests/test_efolds_inflation.py
tests/test_equations.py
tests/test_events.py
tests/test_exceptionhandling.py
tests/test_inflation.py
tests/test_initialconditions.py
tests/test_perturbations.py
tests/test_potentials.py
tests/test_time_inflation.py
tests/test_tools.py
tests/test_version.py
primpy-2.18.2.dist-info/METADATA
primpy-2.18.2.dist-info/WHEEL
primpy-2.18.2.dist-info/top_level.txt
primpy-2.18.2.dist-info/RECORD
