Metadata-Version: 2.4
Name: primpy
Version: 2.18.2
Summary: primpy: Calculations for the primordial Universe.
Author: Lukas Hergt
Author-email: lukas.hergt@ijclab.in2p3.fr
License: MIT
Keywords: PPS,cosmic inflation,initial conditions for inflation,kinetic dominance
Classifier: Development Status :: 5 - Production/Stable
Classifier: Intended Audience :: Science/Research
Classifier: License :: OSI Approved :: MIT License
Classifier: Natural Language :: English
Classifier: Operating System :: OS Independent
Classifier: Programming Language :: Python :: 3.8
Classifier: Programming Language :: Python :: 3.9
Classifier: Programming Language :: Python :: 3.10
Classifier: Programming Language :: Python :: 3.11
Classifier: Programming Language :: Python :: 3.12
Classifier: Topic :: Scientific/Engineering :: Physics
Classifier: Topic :: Scientific/Engineering :: Astronomy
License-File: LICENSE
Requires-Dist: numpy
Requires-Dist: scipy
Requires-Dist: pyoscode
Dynamic: author
Dynamic: author-email
Dynamic: classifier
Dynamic: description
Dynamic: keywords
Dynamic: license
Dynamic: license-file
Dynamic: requires-dist
Dynamic: summary
